<?xml version="1.0" encoding="UTF-8" standalone="yes"?>
<trpDocMetadata>
    <docId>569254</docId>
    <title>PKEL'V.=5239#145</title>
    <uploadTimestamp>1610378978696</uploadTimestamp>
    <uploader>szucs.kata.agnes@gmail.com</uploader>
    <uploaderId>63384</uploaderId>
    <nrOfPages>4</nrOfPages>
    <pageId>23182178</pageId>
    <url>https://files.transkribus.eu/Get?id=BZTUERVOMRSJKYCQBBVRVLRS&amp;fileType=view</url>
    <thumbUrl>https://files.transkribus.eu/Get?id=BZTUERVOMRSJKYCQBBVRVLRS&amp;fileType=thumb</thumbUrl>
    <status>0</status>
    <fimgStoreColl>TrpDoc_DEA_569254</fimgStoreColl>
    <origDocId>0</origDocId>
    <collectionList>
        <colList>
            <colId>45634</colId>
            <colName>kiss_jozsef</colName>
            <description>created by eszter.mihaly@gmail.com</description>
            <crowdsourcing>false</crowdsourcing>
            <elearning>false</elearning>
            <nrOfDocuments>0</nrOfDocuments>
        </colList>
    </collectionList>
</trpDocMetadata>
